LICENSE
MANIFEST.in
README.md
setup.py
quart_doh/__init__.py
quart_doh/client.py
quart_doh/constants.py
quart_doh/dns_resolver.py
quart_doh/server.py
quart_doh/utils.py
quart_doh.egg-info/PKG-INFO
quart_doh.egg-info/SOURCES.txt
quart_doh.egg-info/dependency_links.txt
quart_doh.egg-info/entry_points.txt
quart_doh.egg-info/requires.txt
quart_doh.egg-info/top_level.txt