Metadata-Version: 2.1
Name: quart-doh
Version: 0.1.0
Summary: A client and proxy implementation of https://tools.ietf.org/html/draft-ietf-doh-dns-over-https-13
Home-page: https://github.com/treussart/quart-doh
Author: Matthieu Treussart
Author-email: matthieu@treussart.com
License: BSD License
Keywords: doh dns https
Platform: UNKNOWN
Classifier: Environment :: Web Environment
Classifier: License :: OSI Approved :: BSD License
Classifier: Programming Language :: Python :: 3.7
Classifier: Topic :: Internet :: Name Service (DNS)
Classifier: Topic :: Internet :: WWW/HTTP :: HTTP Servers
Classifier: Topic :: Utilities
